graphene_federation/__init__.py
graphene_federation/composable_directive.py
graphene_federation/entity.py
graphene_federation/schema.py
graphene_federation/service.py
graphene_federation/apollo_versions/__init__.py
graphene_federation/apollo_versions/v1_0.py
graphene_federation/apollo_versions/v2_0.py
graphene_federation/apollo_versions/v2_1.py
graphene_federation/apollo_versions/v2_10.py
graphene_federation/apollo_versions/v2_11.py
graphene_federation/apollo_versions/v2_2.py
graphene_federation/apollo_versions/v2_3.py
graphene_federation/apollo_versions/v2_4.py
graphene_federation/apollo_versions/v2_5.py
graphene_federation/apollo_versions/v2_6.py
graphene_federation/apollo_versions/v2_7.py
graphene_federation/apollo_versions/v2_8.py
graphene_federation/apollo_versions/v2_9.py
graphene_federation/apollo_versions/version.py
graphene_federation/directives/__init__.py
graphene_federation/directives/authenticated.py
graphene_federation/directives/context.py
graphene_federation/directives/cost.py
graphene_federation/directives/extends.py
graphene_federation/directives/external.py
graphene_federation/directives/from_context.py
graphene_federation/directives/inaccessible.py
graphene_federation/directives/interface_object.py
graphene_federation/directives/key.py
graphene_federation/directives/list_size.py
graphene_federation/directives/override.py
graphene_federation/directives/policy.py
graphene_federation/directives/provides.py
graphene_federation/directives/requires.py
graphene_federation/directives/requires_scopes.py
graphene_federation/directives/shareable.py
graphene_federation/directives/tag.py
graphene_federation/directives/utils.py
graphene_federation/scalars/__init__.py
graphene_federation/scalars/_any.py
graphene_federation/scalars/federation_context_field_value.py
graphene_federation/scalars/federation_policy.py
graphene_federation/scalars/federation_scope.py
graphene_federation/scalars/field_set_v1.py
graphene_federation/scalars/field_set_v2.py
graphene_federation-3.3.0.dist-info/licenses/LICENSE.txt
graphene_federation-3.3.0.dist-info/METADATA
graphene_federation-3.3.0.dist-info/WHEEL
graphene_federation-3.3.0.dist-info/top_level.txt
graphene_federation-3.3.0.dist-info/RECORD
