Metadata-Version: 2.4
Name: graphene-federation
Version: 3.3.0
Summary: Federation implementation for graphene
Home-page: https://github.com/graphql-python/graphene-federation
Download-URL: https://github.com/graphql-python/graphene-federation/archive/3.3.0.tar.gz
Author: Igor Kasianov
Author-email: super.hang.glider@gmail.com
License: MIT
Keywords: graphene,graphql,gql,federation
Classifier: Development Status :: 5 - Production/Stable
Classifier: Intended Audience :: Developers
Classifier: Topic :: Software Development :: Libraries
Classifier: Programming Language :: Python :: 3.9
Classifier: Programming Language :: Python :: 3.10
Classifier: Programming Language :: Python :: 3.11
Classifier: Programming Language :: Python :: 3.12
Classifier: Programming Language :: Python :: 3.13
Classifier: Programming Language :: Python :: 3.14
License-File: LICENSE.txt
Requires-Dist: graphene>=3.1
Requires-Dist: graphql-core>=3.1
Requires-Dist: graphene-directives>=0.5.0
Provides-Extra: test
Requires-Dist: pytest==8.4.2; extra == "test"
Requires-Dist: pytest-cov; extra == "test"
Provides-Extra: dev
Requires-Dist: black==23.12.1; extra == "dev"
Requires-Dist: flake8==7.3.0; extra == "dev"
Requires-Dist: mypy==1.18.2; extra == "dev"
Requires-Dist: pytest==8.4.2; extra == "dev"
Requires-Dist: pytest-cov; extra == "dev"
Dynamic: author
Dynamic: author-email
Dynamic: classifier
Dynamic: description
Dynamic: description-content-type
Dynamic: download-url
Dynamic: home-page
Dynamic: keywords
Dynamic: license
Dynamic: license-file
Dynamic: provides-extra
Dynamic: requires-dist
Dynamic: summary
